COPYING
MANIFEST.in
README.rst
setup.py
doc/Makefile
doc/source/.nojekyll
doc/source/TSapproximation.rst
doc/source/changes.rst
doc/source/conf.py
doc/source/download.rst
doc/source/examples.rst
doc/source/index.rst
doc/source/indexlatex.rst
doc/source/introduction.rst
doc/source/quickstart.rst
doc/source/reference.rst
doc/source/reference_autodoc.rst
doc/source/figures/bec1.png
doc/source/figures/bec2.png
doc/source/figures/imaginary.png
trottersuzuki/__init__.py
trottersuzuki/classes_extension.py
trottersuzuki/docstring.i
trottersuzuki/numpy.i
trottersuzuki/tools.py
trottersuzuki/trottersuzuki.i
trottersuzuki/trottersuzuki.py
trottersuzuki/trottersuzuki_wrap.cxx
trottersuzuki.egg-info/PKG-INFO
trottersuzuki.egg-info/SOURCES.txt
trottersuzuki.egg-info/dependency_links.txt
trottersuzuki.egg-info/requires.txt
trottersuzuki.egg-info/top_level.txt
trottersuzuki/src/common.cpp
trottersuzuki/src/common.h
trottersuzuki/src/cpucartesian.cpp
trottersuzuki/src/cpucylindrical.cpp
trottersuzuki/src/cpukernel.cpp
trottersuzuki/src/gpucartesian.cu
trottersuzuki/src/gpukernel.cu
trottersuzuki/src/kernel.h
trottersuzuki/src/model.cpp
trottersuzuki/src/solver.cpp
trottersuzuki/src/trottersuzuki.h