Metadata-Version: 1.1
Name: trottersuzuki
Version: 1.6.2
Summary: Massively Parallel Trotter-Suzuki Solver
Home-page: http://trotter-suzuki-mpi.github.io/
Author: Peter Wittek, Luca Calderaro
Author-email: peterwittek@users.noreply.github.com
License: GPL3
Platform: unix
Platform: windows
Classifier: License :: OSI Approved :: GNU General Public License v3 (GPLv3)
Classifier: Operating System :: OS Independent
Classifier: Development Status :: 5 - Production/Stable
Classifier: Topic :: Scientific/Engineering :: Physics
Classifier: Intended Audience :: Science/Research
Classifier: Programming Language :: Python
Classifier: Programming Language :: C++
